sum_4197/__init__.py
sum_4197-0.0.1.dist-info/METADATA
sum_4197-0.0.1.dist-info/WHEEL
sum_4197-0.0.1.dist-info/license.txt
sum_4197-0.0.1.dist-info/top_level.txt
sum_4197-0.0.1.dist-info/RECORD
